{
  "title": "PCE Nedir? Fed'in Enflasyon Göstergesi Dolar'ı Nasıl Etkiler? #Shorts",
  "description": "PCE nedir, neden Fed CPI yerine bunu izler ve 25 Haziran verisi dolar, altın, TL'yi nasıl etkiler? Karşılaştırma tablosuyla açıkladık.\n\nTüm yazı: https://parafomo.com/blog/pce-nedir-fed-enflasyon-gostergesi/\n\n#Shorts #finans #yatırım #para #ekonomi #parafomo",
  "tags": [
    "finans",
    "yatırım",
    "para",
    "ekonomi",
    "parafomo"
  ],
  "file": "/root/parafomo/public/social/short-pce-nedir-fed-enflasyon-gostergesi.mp4",
  "slug": "pce-nedir-fed-enflasyon-gostergesi",
  "voice": "edge:tr-TR-AhmetNeural",
  "format": "",
  "video_id": "Tk3LJGEi3n4",
  "youtube_url": "https://youtube.com/shorts/Tk3LJGEi3n4"
}