{
  "title": "ABD'nin Notu Düştü: Paranın Yönü Nereye Gidiyor? #Shorts",
  "description": "Moody's'in ABD kredi notu kararı dolar, altın ve Türk yatırımcısı için ne anlama geliyor? Mekanizmayı sade anlattık.\n\nDaha fazlası: https://parafomo.com\n\n#Shorts #Moody's #ABD kredi notu #altın #dolar #Türk yatırımcısı",
  "tags": [
    "Moody's",
    "ABD kredi notu",
    "altın",
    "dolar",
    "Türk yatırımcısı",
    "ParaFOMO",
    "parafomo"
  ],
  "file": "/root/parafomo/public/social/short-abd-nin-notu-dustu-paranin-yonu-nereye-gidiyor.mp4",
  "slug": "abd-nin-notu-dustu-paranin-yonu-nereye-gidiyor",
  "voice": "google:tr-TR-Chirp3-HD-Zubenelgenubi",
  "format": "news_reaction",
  "video_id": "HhSE_7kSNpA",
  "youtube_url": "https://youtube.com/shorts/HhSE_7kSNpA"
}